melt_to_gephi/__init__.py
melt_to_gephi/cli.py
melt_to_gephi/melt_to_gephi.py
melt_to_gephi/utils.py
melt_to_gephi-0.1.1.dist-info/AUTHORS.rst
melt_to_gephi-0.1.1.dist-info/LICENSE
melt_to_gephi-0.1.1.dist-info/METADATA
melt_to_gephi-0.1.1.dist-info/WHEEL
melt_to_gephi-0.1.1.dist-info/entry_points.txt
melt_to_gephi-0.1.1.dist-info/top_level.txt
melt_to_gephi-0.1.1.dist-info/RECORD
