Metadata-Version: 2.1
Name: melt-to-gephi
Version: 0.1.1
Summary: A simpler way of restructituring Meltwater data to a gephi ready data file
Home-page: https://github.com/4bic/melt_to_gephi
Author: Robin Kiplangat
Author-email: robyne.kiplangat@gmail.com
License: MIT license
Keywords: meltgephi,gephi,meltwater
Platform: UNKNOWN
Classifier: Development Status :: 2 - Pre-Alpha
Classifier: Intended Audience :: Developers
Classifier: License :: OSI Approved :: MIT License
Classifier: Natural Language :: English
Classifier: Programming Language :: Python :: 3
Classifier: Programming Language :: Python :: 3.5
Classifier: Programming Language :: Python :: 3.6
Classifier: Programming Language :: Python :: 3.7
Classifier: Programming Language :: Python :: 3.8
Requires-Python: >=3.5
Requires-Dist: Click (>=7.0)
